design/lif_neuron.v
module lif_neuron (
    input clk,
    input rst,

    input spike_in,
    input signed [7:0] weight,      // wire and not parameter as if we wanna use for SNN purposes then the weight for different neurons while scaling should be variable
    input signed [7:0] threshold,   // same idea as weight
    input signed [7:0] leak,        // also same idea
    input [3:0] refractory_cycles,

    output reg spike_out
);

    // State
    reg signed [7:0] membrane;
    reg signed [7:0] next_membrane;
    reg [3:0] refractory;

    // Combinational: next state
    always @(*) begin
        // leak
        next_membrane = membrane - leak;

        // integrate spike
        if (spike_in)
            next_membrane = next_membrane + weight;

        // clamp to 0 as resting potential so it doesnt go to negative voltage on leak
        if (next_membrane < 0)
            next_membrane = 0;
    end

    // Sequential: state update
    always @(posedge clk or posedge rst) begin
        if (rst) begin
            membrane   <= 0;
            spike_out  <= 0;
            refractory <= 0;
        end else begin
            // default: spike is a 1-cycle pulse
            spike_out <= 0;

            // Refractory period
            if (refractory != 0) begin
                refractory <= refractory - 1;
                // hold membrane at reset
                membrane <= 0;
            end
            else begin
                // Threshold check
                if (next_membrane >= threshold) begin
                    spike_out  <= 1;
                    membrane   <= 0;
                    refractory <= refractory_cycles;
                end
                else begin
                    membrane <= next_membrane;
                end
            end
        end
    end

endmodule

testbench/lif_neuron_tb.v
`timescale 1ns/1ps

module lif_neuron_tb;

// Inputs
reg clk;
reg rst;
reg spike_in;
reg signed [7:0] weight;
reg signed [7:0] threshold;
reg signed [7:0] leak;
reg [3:0] refractory_cycles;

// Output
wire spike_out;

// Instantiate neuron module
lif_neuron uut (
    .clk(clk),
    .rst(rst),
    .spike_in(spike_in),
    .weight(weight),
    .threshold(threshold),
    .leak(leak),
    .refractory_cycles(refractory_cycles),
    .spike_out(spike_out)
);

// Clock: 10ns period
always #5 clk = ~clk;


// Spike generator
task send_spike;
begin
    @(posedge clk);
    spike_in = 1;

    @(posedge clk);
    spike_in = 0;
end
endtask


// Simulation
initial begin
    // Dump waveform
    $dumpfile("lif_neuron.vcd");
    $dumpvars(0, lif_neuron_tb);

    // Init
    clk = 0;
    rst = 1;
    spike_in = 0;

    weight    = 8'sd5;
    threshold = 8'sd10;
    leak      = 8'sd1;
    refractory_cycles = 4;

    // Reset for a few cycles
    repeat (3) @(posedge clk);
    rst = 0;

    // Test 1: Single spike
    send_spike();   // membrane value should increase by 5 but leak occurs simultaneously so membrane increases by 5-1 = 4
    repeat (3) @(posedge clk); // allow leak

    // Test 2: Multiple spikes and trigger firing
    send_spike();   // +4 -> 4
    send_spike();   // +4 -> 8 is what should happen but according to the definition of send_spike() it goes to 1 on rising edge of clock cycle N and 0 on rising edge of clock cycle N+1 this one more leak occurs before the next send_spike() thus +4-1 -> 7
    send_spike();   // +4-1 -> 10 which is equal to the threshold so it spikes and the value of membrane goes to 0
    send_spike();   // nothing happens as during refractory period
    
    // Wait (refractory) 
    repeat (6) @(posedge clk);

    // Test 3: Spike after refractory
    send_spike();
    send_spike();

    repeat (10) @(posedge clk);

    $finish;
end


// Debug print on terminal
always @(posedge clk) begin
    $display("t=%0t | spike_in=%b | membrane=%0d | spike_out=%b",
             $time, spike_in, uut.membrane, spike_out);
end

endmodule

lif_neuron.vcd
$date
	Mon Mar 23 18:21:09 2026
$end
$version
	Icarus Verilog
$end
$timescale
	1ps
$end
$scope module lif_neuron_tb $end
$var wire 1 ! spike_out $end
$var reg 1 " clk $end
$var reg 8 # leak [7:0] $end
$var reg 4 $ refractory_cycles [3:0] $end
$var reg 1 % rst $end
$var reg 1 & spike_in $end
$var reg 8 ' threshold [7:0] $end
$var reg 8 ( weight [7:0] $end
$scope module uut $end
$var wire 1 " clk $end
$var wire 8 ) leak [7:0] $end
$var wire 4 * refractory_cycles [3:0] $end
$var wire 1 % rst $end
$var wire 1 & spike_in $end
$var wire 8 + threshold [7:0] $end
$var wire 8 , weight [7:0] $end
$var reg 8 - membrane [7:0] $end
$var reg 8 . next_membrane [7:0] $end
$var reg 4 / refractory [3:0] $end
$var reg 1 ! spike_out $end
$upscope $end
$scope task send_spike $end
$upscope $end
$upscope $end
$enddefinitions $end
$comment Show the parameter values. $end
$dumpall
$end
#0
$dumpvars
b0 /
b0 .
b0 -
b101 ,
b1010 +
b100 *
b1 )
b101 (
b1010 '
0&
1%
b100 $
b1 #
0"
0!
$end
#5000
1"
#10000
0"
#15000
1"
#20000
0"
#25000
0%
1"
#30000
0"
#35000
b100 .
1&
1"
#40000
0"
#45000
b100 -
b11 .
0&
1"
#50000
0"
#55000
b10 .
b11 -
1"
#60000
0"
#65000
b1 .
b10 -
1"
#70000
0"
#75000
b0 .
b1 -
1"
#80000
0"
#85000
b0 -
b100 .
1&
1"
#90000
0"
#95000
b100 -
b11 .
0&
1"
#100000
0"
#105000
b11 -
b111 .
1&
1"
#110000
0"
#115000
b111 -
b110 .
0&
1"
#120000
0"
#125000
b110 -
b1010 .
1&
1"
#130000
0"
#135000
b100 /
b0 -
1!
b0 .
0&
1"
#140000
0"
#145000
b11 /
0!
b100 .
1&
1"
#150000
0"
#155000
b10 /
b0 .
0&
1"
#160000
0"
#165000
b1 /
1"
#170000
0"
#175000
b0 /
1"
#180000
0"
#185000
1"
#190000
0"
#195000
1"
#200000
0"
#205000
1"
#210000
0"
#215000
1"
#220000
0"
#225000
b100 .
1&
1"
#230000
0"
#235000
b100 -
b11 .
0&
1"
#240000
0"
#245000
b11 -
b111 .
1&
1"
#250000
0"
#255000
b111 -
b110 .
0&
1"
#260000
0"
#265000
b101 .
b110 -
1"
#270000
0"
#275000
b100 .
b101 -
1"
#280000
0"
#285000
b11 .
b100 -
1"
#290000
0"
#295000
b10 .
b11 -
1"
#300000
0"
#305000
b1 .
b10 -
1"
#310000
0"
#315000
b0 .
b1 -
1"
#320000
0"
#325000
b0 .
b0 -
1"
